language_tool_python/__init__.py
language_tool_python/__main__.py
language_tool_python/config_file.py
language_tool_python/download_lt.py
language_tool_python/exceptions.py
language_tool_python/language_tag.py
language_tool_python/logging.toml
language_tool_python/match.py
language_tool_python/py.typed
language_tool_python/server.py
language_tool_python/utils.py
language_tool_python-3.2.1.dist-info/licenses/LICENSE
language_tool_python-3.2.1.dist-info/METADATA
language_tool_python-3.2.1.dist-info/WHEEL
language_tool_python-3.2.1.dist-info/entry_points.txt
language_tool_python-3.2.1.dist-info/top_level.txt
language_tool_python-3.2.1.dist-info/RECORD
