Metadata-Version: 2.4
Name: language_tool_python
Version: 3.2.1
Summary: Checks grammar using LanguageTool.
Author-email: Jack Morris <jxmorris12@gmail.com>
Maintainer-email: mdevolde <martin.devolder2@gmail.com>
License-Expression: GPL-3.0-only
Project-URL: repository, https://github.com/jxmorris12/language_tool_python.git
Project-URL: documentation, https://language-tool-python.readthedocs.io/en/latest/
Project-URL: changelog, https://github.com/jxmorris12/language_tool_python/blob/master/CHANGELOG.md
Keywords: python,nlp,grammar,languagetool,grammar-checker,spellchecker,grammar-parser
Classifier: Programming Language :: Python :: 3
Classifier: Programming Language :: Python :: 3.9
Classifier: Programming Language :: Python :: 3.10
Classifier: Programming Language :: Python :: 3.11
Classifier: Programming Language :: Python :: 3.12
Classifier: Programming Language :: Python :: 3.13
Classifier: Programming Language :: Python :: 3.14
Classifier: Operating System :: OS Independent
Classifier: Topic :: Software Development :: Libraries :: Python Modules
Classifier: Topic :: Text Processing :: Linguistic
Requires-Python: >=3.9
License-File: LICENSE
Requires-Dist: requests
Requires-Dist: tqdm
Requires-Dist: packaging
Requires-Dist: psutil
Requires-Dist: toml
Dynamic: license-file
